MANIFEST.in
README.md
setup.py
gdwrap/Gdwrap.py
gdwrap/__init__.py
gdwrap.egg-info/PKG-INFO
gdwrap.egg-info/SOURCES.txt
gdwrap.egg-info/dependency_links.txt
gdwrap.egg-info/not-zip-safe
gdwrap.egg-info/requires.txt
gdwrap.egg-info/top_level.txt