Metadata-Version: 1.0
Name: gdwrap
Version: 0.0.2
Summary: gdwrap is wrapper libs for Google Drive Rest API.
Home-page: https://github.com/nabeen/gdwrap
Author: nabeen
Author-email: watanabe_kenichiro@hasigo.co.jp
License: UNKNOWN
Platform: UNKNOWN
